odoo9_addon_web_tree_many2one_clickable-9.0.1.0.0-py2.7-nspkg.pth
odoo_addons/web_tree_many2one_clickable/__openerp__.py
odoo_addons/web_tree_many2one_clickable/__init__.py
odoo_addons/web_tree_many2one_clickable/README.rst
odoo_addons/web_tree_many2one_clickable/views/asset.xml
odoo_addons/web_tree_many2one_clickable/data/ir_config_parameter.xml
odoo_addons/web_tree_many2one_clickable/static/description/icon.png
odoo_addons/web_tree_many2one_clickable/static/src/js/web_tree_many2one_clickable.js
odoo9_addon_web_tree_many2one_clickable-9.0.1.0.0.dist-info/top_level.txt
odoo9_addon_web_tree_many2one_clickable-9.0.1.0.0.dist-info/WHEEL
odoo9_addon_web_tree_many2one_clickable-9.0.1.0.0.dist-info/RECORD
odoo9_addon_web_tree_many2one_clickable-9.0.1.0.0.dist-info/metadata.json
odoo9_addon_web_tree_many2one_clickable-9.0.1.0.0.dist-info/DESCRIPTION.rst
odoo9_addon_web_tree_many2one_clickable-9.0.1.0.0.dist-info/METADATA
odoo9_addon_web_tree_many2one_clickable-9.0.1.0.0.dist-info/namespace_packages.txt
